MANIFEST.in
README.md
VERSION
requirements.txt
setup.py
last_model/__init__.py
last_model/_utils.py
last_model/config.py
last_model/data_loader.py
last_model/init_functions.py
last_model/last.py
last_model/model_functions.py
last_model/params.py
last_model/read_functions.py
last_model.egg-info/PKG-INFO
last_model.egg-info/SOURCES.txt
last_model.egg-info/dependency_links.txt
last_model.egg-info/not-zip-safe
last_model.egg-info/requires.txt
last_model.egg-info/top_level.txt
last_model/ext/__init__.py
last_model/ext/infiltration.py
last_model/ext/preferential_flow.py