Metadata-Version: 2.1
Name: last-model
Version: 0.1.1
Summary: LAST model Python implementation
Home-page: UNKNOWN
Author: Mirko Mälicke, Alexander Sternagel
Author-email: mirko.maelicke@kit.edu
License: UNKNOWN
Platform: UNKNOWN
